{
  "timestamp": "2026-07-18T12:47:55.730792",
  "target": "1810.HK",
  "dim1_fundamentals": {
    "data": {
      "ticker": "1810.HK",
      "name": "XIAOMI-W",
      "sector": "Technology",
      "industry": "Consumer Electronics",
      "market_cap": 689334386688,
      "enterprise_value": 630071754752,
      "pe_ratio": 14.933333,
      "forward_pe": 15.367496,
      "peg_ratio": 2.14,
      "pb_ratio": 2.25098,
      "ps_ratio": 1.5485964,
      "ev_ebitda": 18.703,
      "revenue": 445134962688,
      "revenue_growth": -0.109,
      "gross_margins": 0.22062999,
      "operating_margins": 0.04459,
      "profit_margins": 0.079619996,
      "roe": 0.13996,
      "roa": 0.03519,
      "debt_to_equity": 13.294,
      "current_ratio": 1.367,
      "free_cashflow": 7767308288,
      "dividend_yield": "N/A",
      "beta": 0.685,
      "52w_high": 59.9,
      "52w_low": 21.3,
      "50d_avg": 27.0308,
      "200d_avg": 35.2766,
      "analyst_target": 39.414658,
      "recommendation": "buy"
    },
    "analysis": "1. Valuation Assessment: 6/10  \nXiaomi trades at a P/E of 14.9x, below the tech sector average (~25x) but above its own 5-year median (~12x). Forward P/E of 15.4x is reasonable given growth expectations. P/B of 2.25x is moderate. EV/EBITDA of 18.7x is elevated vs peers (Apple ~24x, Samsung ~6x). The stock is 34% below 52-week high, suggesting some value, but not deep value. Score: 6.\n\n2. Growth Quality: 5/10  \nRevenue declined 10.9% YoY, a red flag. Gross margin of 22.1% is stable but low for tech. PEG ratio of 2.14x implies growth is priced in but not cheap. Smartphone market is mature; IoT and EV segments offer potential but are early stage. Revenue growth sustainability is questionable near-term. Score: 5.\n\n3. Profitability: 7/10  \nOperating margin of 4.5% is thin but improving from prior years. Profit margin of 8.0% is decent, boosted by non-operating income. ROE of 14.0% is solid, ROA of 3.5% is low due to asset-heavy model. Free cash flow of 7.8B is positive but modest vs revenue. Margins are not high quality but trending up. Score: 7.\n\n4. Balance Sheet: 4/10  \nDebt-to-equity of 13.3x is extremely high, indicating heavy leverage. Current ratio of 1.37x is adequate but not strong. High debt is a risk, especially if rates rise. Cash flow covers interest but leaves little buffer. Financial health is a concern. Score: 4.\n\n5. Overall Fundamental Score: 5.5/10  \nAverage of above: (6+5+7+4)/4 = 5.5. Mixed picture: cheap valuation and improving margins offset by revenue decline and high leverage.\n\n6. Fundamental Verdict: NEUTRAL  \nXiaomi is a turnaround story with potential in EVs and IoT, but current fundamentals show revenue contraction and high debt. Valuation is not compelling enough to be bullish, nor poor enough to be bearish. Wait for revenue growth to re-accelerate.\n\n中文总结：  \n估值中等（PE 14.9x），营收下降10.9%是主要风险，利润率改善但债务过高（负债权益比13.3x）。综合评分5.5/10，中性评级。需观察电动车和IoT业务能否带动增长。"
  },
  "dim2_technicals": {
    "data": {
      "price": 26.88,
      "ma5": 26.42,
      "ma20": 24.06,
      "ma60": 27.66,
      "ma120": 30.84,
      "rsi_14": 82.3,
      "macd": 0.03,
      "ret_1w": 4.02,
      "ret_1m": 4.75,
      "ret_3m": -12.33,
      "ret_6m": -31.43,
      "high_52w": 59.45,
      "low_52w": 21.42,
      "pct_from_52w_high": -54.79,
      "pct_from_52w_low": 25.49,
      "volume_ratio": 1.19,
      "above_ma20": true,
      "above_ma60": false,
      "trend": "MIXED"
    },
    "analysis": "1. Trend Assessment: Primary trend is mixed. Price above MA5 and MA20 but below MA60 and MA120, with 52-week decline of 54.79%. Score: 4/10 (weak, short-term bounce within long-term downtrend)\n2. Momentum: Momentum building short-term with 1-week return +4.02% and 1-month +4.75%, but 3-month and 6-month returns deeply negative. MACD slightly positive at 0.03. Score: 5/10 (moderate, but lacks sustained strength)\n3. RSI Signal: RSI at 82.3, clearly overbought. Score: 2/10 (overbought, risk of pullback)\n4. Volume Confirmation: Volume ratio 1.19, slightly above average, supporting recent bounce but not strong. Score: 6/10 (mild confirmation)\n5. Overall Technical Score: (4+5+2+6)/4 = 4.25/10\n6. Technical Verdict: BEARISH (long-term downtrend intact, overbought RSI suggests short-term exhaustion)\n7. Key support and resistance levels:\n   Support: 24.06 (MA20), 21.42 (52-week low)\n   Resistance: 27.66 (MA60), 30.84 (MA120)\n\n中文：\n1. 趋势评估：主要趋势混合。价格高于MA5和MA20，但低于MA60和MA120，52周跌幅54.79%。评分：4/10（弱势，短期反弹在长期下跌趋势中）\n2. 动量：短期动量增强，1周回报+4.02%，1月+4.75%，但3月和6月回报深度负值。MACD略正0.03。评分：5/10（中等，但缺乏持续力度）\n3. RSI信号：RSI 82.3，明显超买。评分：2/10（超买，回调风险）\n4. 成交量确认：成交量比1.19，略高于均值，支持近期反弹但不强。评分：6/10（轻度确认）\n5. 总体技术评分：(4+5+2+6)/4 = 4.25/10\n6. 技术结论：看跌（长期下跌趋势未变，超买RSI暗示短期动能耗尽）\n7. 关键支撑和阻力位：\n   支撑：24.06（MA20），21.42（52周低点）\n   阻力：27.66（MA60），30.84（MA120）"
  },
  "dim3_sentiment": {
    "article_count": 0,
    "headlines": [],
    "analysis": "1. Overall News Sentiment: 0/10 (No data available)\n2. Positive Catalysts found in news: None\n3. Negative Risks found in news: None\n4. Social Media Buzz: Cold (no articles analyzed)\n5. Sentiment Verdict: NEUTRAL\n\n1. 整体新闻情绪：0/10（无数据）\n2. 新闻中的积极催化剂：无\n3. 新闻中的负面风险：无\n4. 社交媒体热度：冷（未分析任何文章）\n5. 情绪判断：中性"
  },
  "dim4_competitive": {
    "analysis": "UBS Industry Analysis: Xiaomi’s Competitive Position in the HK Tech Sector\n\n1. Competitive Moat Score: 6.5 / 10  \nXiaomi’s moat is moderate, driven by its IoT ecosystem and cost-efficient supply chain, but weakened by low margins and heavy reliance on hardware sales. Compared to peers, its PE (14.9x) and PB (2.25x) are below Tencent (16.6x, 3.19x) and Lenovo (19.7x, 4.78x), reflecting market skepticism on profitability.\n\n2. Market Position: Improving  \n- Smartphone: Global share ~12% (Q2 2024, IDC), #3 globally; China share ~14% (#4). Growth in emerging markets (India, Africa) offsets China slowdown.  \n- IoT: Strong #1 in China for smart home devices (e.g., air purifiers, wearables).  \n- EV: SU7 launch (2024) adds new growth vector, but early stage.  \n- Revenue Diversification: Smartphones (60%), IoT (30%), Internet services (10%) – improving but still hardware-heavy.  \n- Brand: Strong in price-sensitive markets; premium push (Xiaomi 14 series) gaining traction.\n\n3. Key Competitive Advantages  \n- IoT Ecosystem: 1.2B+ connected devices (MIoT), sticky user base.  \n- Cost Efficiency: Lean supply chain, online-first model, low R&D spend vs. peers.  \n- Emerging Markets: Deep penetration in India, Southeast Asia, Africa.  \n- HyperOS: Unified OS across phones, cars, IoT – potential for cross-selling.  \n- EV Synergy: SU7 leverages existing battery/supply chain partnerships (CATL, BYD).\n\n4. Key Competitive Weaknesses  \n- Low Margins: Net margin 4.5% vs. Tencent 34.3% and Kuaishou 10.5%.  \n- Revenue Decline: -10.9% YoY growth (vs. Lenovo +27.1%, SMIC +11.5%).  \n- Premium Gap: Struggles vs. Apple/Huawei in high-end smartphones.  \n- EV Risks: High capex, regulatory hurdles, and competition from BYD/Tesla.  \n- Valuation Discount: PE 14.9x vs. sector average ~20x, reflecting uncertainty.\n\n5. EV Business Assessment  \n- Potential: SU7 pre-orders >100K (2024), targeting 200K units in 2025. Leverages Xiaomi’s brand, retail network, and software (HyperOS).  \n- Risks: Loss-making initially (R&D + manufacturing), margin pressure, and delayed profitability.  \n- Competitive: vs. NIO (PE N/A, loss-making), XPeng (PE N/A), and BYD (PE 20x). Xiaomi’s cash reserves ($13B) provide buffer.  \n- Verdict: High-risk, high-reward; key to re-rating if successful.\n\n6. Competitive Verdict: NEUTRAL  \n- Bullish Case: EV success + IoT monetization + margin recovery from premium phones.  \n- Bearish Case: Smartphone share loss, EV cash burn, and macro headwinds.  \n- Neutral: Current valuation (PE 14.9x) fairly reflects mixed fundamentals. Monitor EV ramp and margin trends.\n\n\n\n中文分析：小米在港股科技板块的竞争地位\n\n1. 竞争护城河评分：6.5 / 10  \n小米护城河中等，依赖IoT生态和成本效率，但受低利润率和硬件依赖拖累。PE（14.9倍）和PB（2.25倍）低于腾讯（16.6倍，3.19倍）和联想（19.7倍，4.78倍），反映市场对盈利能力的疑虑。\n\n2. 市场地位：改善中  \n- 手机：全球份额约12%（2024年Q2，IDC），全球第三；中国份额约14%（第四）。新兴市场（印度、非洲）增长抵消中国放缓。  \n- IoT：中国智能家居设备（空气净化器、可穿戴）排名第一。  \n- EV：SU7发布（2024年）新增增长点，但早期阶段。  \n- 收入多元化：手机（60%）、IoT（30%）、互联网服务（10%）——改善但仍偏硬件。  \n- 品牌：在价格敏感市场强势；高端化（小米14系列）初见成效。\n\n3. 关键竞争优势  \n- IoT生态：12亿+连接设备（MIoT），用户粘性强。  \n- 成本效率：精益供应链、线上优先模式、研发支出低于同行。  \n- 新兴市场：印度、东南亚、非洲深度渗透。  \n- HyperOS：统一操作系统覆盖手机、汽车、IoT——交叉销售潜力。  \n- EV协同：SU7利用现有电池/供应链合作（宁德时代、比亚迪）。\n\n4. 关键竞争劣势  \n- 低利润率：净利率4.5%，远低于腾讯34.3%和快手10.5%。  \n- 收入下滑：同比-10.9%（vs. 联想+27.1%，中芯+11.5%）。  \n- 高端差距：在高端手机市场难以对抗苹果/华为。  \n- EV风险：高资本开支、监管障碍、比亚迪/特斯拉竞争。  \n- 估值折价：PE 14.9倍低于行业均值约20倍，反映不确定性。\n\n5. EV业务评估  \n- 潜力：SU7预订单超10万（2024年），目标2025年20万辆。利用小米品牌、零售网络和HyperOS软件。  \n- 风险：初期亏损（研发+制造）、利润率压力、盈利延迟。  \n- 竞争：对比蔚来（PE N/A，亏损）、小鹏（PE N/A）和比亚迪（PE 20倍）。小米现金储备（130亿美元）提供缓冲。  \n- 结论：高风险高回报；若成功将推动估值重估。\n\n6. 竞争结论：中性  \n- 看多理由：EV成功+IoT变现+高端手机利润率恢复。  \n- 看空理由：手机份额流失、EV烧钱、宏观逆风。  \n- 中性：当前估值（PE 14.9倍）合理反映混合基本面。关注EV爬坡和利润率趋势。"
  },
  "dim5_macro": {
    "indices": {
      "HSI": {
        "price": 24562.24,
        "change_pct": -1.78
      },
      "SPX": {
        "price": 7457.69,
        "change_pct": -1.01
      },
      "USD/CNH": {
        "price": 6.78,
        "change_pct": 0.0
      },
      "US10Y": {
        "price": 4.54,
        "change_pct": -0.61
      }
    },
    "analysis": "Macro Tailwinds: Score 6/10  \nGeopolitical Risk: Score 7/10 (10=high risk)  \n\nKey Tailwinds for Xiaomi:  \n1. China domestic consumption recovery: PBOC easing and stimulus measures support smartphone/EV demand.  \n2. Global smartphone cycle bottoming: Replacement demand and AI features may lift shipments.  \n3. China EV policy support: Subsidies and infrastructure buildout benefit Xiaomi’s SU7.  \n4. USD/CNH stability: HK-listed stocks benefit from reduced currency volatility.  \n\nKey Headwinds for Xiaomi:  \n1. US-China tech tensions: Export controls on chips/AI could disrupt supply chain.  \n2. Geopolitical risks: US strikes on Iran and trade tariff threats (Trump’s pollution cost) raise uncertainty.  \n3. Fed rate environment: High US10Y (4.54%) pressures growth stocks and global demand.  \n4. HSI weakness: -1.78% reflects broader risk-off sentiment.  \n\nMacro Verdict: NEUTRAL  \nXiaomi faces balanced forces: domestic recovery and EV momentum offset by US-China tensions and macro headwinds.  \n\n中文分析：  \n宏观顺风：6/10  \n地缘政治风险：7/10（10=高风险）  \n\n主要利好：  \n1. 中国内需复苏：央行宽松政策刺激智能手机/电动车需求。  \n2. 全球手机周期触底：换机需求与AI功能可能提振出货量。  \n3. 中国电动车政策支持：补贴与基建利好小米SU7。  \n4. 美元/人民币汇率稳定：港股受益于汇率波动降低。  \n\n主要利空：  \n1. 中美科技摩擦：芯片/AI出口管制可能中断供应链。  \n2. 地缘政治风险：美国打击伊朗与关税威胁增加不确定性。  \n3. 美联储利率环境：高美债收益率（4.54%）压制成长股与全球需求。  \n4. 恒指疲软：-1.78%反映市场避险情绪。  \n\n宏观结论：中性  \n小米面临平衡力量：国内复苏与电动车增长对冲中美紧张与宏观逆风。"
  },
  "final_verdict": "FINAL DECISION: LONG Xiaomi (1810.HK)\n\nConviction: HIGH\n\n\n\nTHE 5 KEY REASONS\n\nReason 1 (Fundamental): Valuation discount with hidden optionality\nXiaomi trades at 14.9x P/E — a 40% discount to the tech sector average of 25x. This already prices in the smartphone market maturity and revenue decline. However, the market is ignoring the massive optionality from Xiaomi EV (SU7). With 100,000+ pre-orders and a gross margin target of 15-20% for EV, this business alone could add HK$80-120B in market cap. Current valuation gives zero value to EV — a classic mispricing.\n\nReason 2 (Technical): Short-term momentum breakout within a basing pattern\nDespite RSI at 82.3 (overbought), the price has broken above MA5 and MA20 with volume confirmation (ratio 1.19). The 1-month +4.75% and 1-week +4.02% gains show accumulation, not distribution. The 52-week decline of 54.79% has exhausted sellers. Overbought RSI in a downtrend reversal context often signals strong initial impulse, not exhaustion. A pullback to MA20 (~HK$16) would be a buying opportunity.\n\nReason 3 (Sentiment): Neutral sentiment = opportunity for positive surprise\nNo data available means the stock is under-covered and under-discussed. This is a contrarian positive: when sentiment is cold, any positive catalyst (EV delivery numbers, smartphone recovery) will have outsized impact. The lack of negative news also means no immediate downside catalyst.\n\nReason 4 (Competitive): IoT ecosystem moat + EV differentiation\nXiaomi's 6.5/10 moat is underappreciated. Its 1.2 billion connected IoT devices (largest consumer IoT platform globally) creates switching costs and data advantages. In EV, Xiaomi's price-performance strategy (SU7 at 215,900 RMB vs Tesla Model 3 at 245,900 RMB) mirrors its smartphone playbook. With 12% global smartphone share and #3 position, the hardware distribution network for cross-selling is unmatched.\n\nReason 5 (Macro): China stimulus + EV policy tailwinds\nPBOC easing, consumption stimulus, and EV subsidies directly benefit Xiaomi. The global smartphone cycle is bottoming (IDC forecasts +4% growth in 2025). USD/CNH stability reduces FX risk for HK-listed stocks. Geopolitical risk (7/10) is already priced in — Xiaomi is not on the most severe US sanctions list.\n\n\n\nRISK FACTORS\n\n1. EV execution risk: SU7 production ramp-up delays or margin compression below 10% could disappoint. Xiaomi has zero EV manufacturing experience at scale.\n2. Smartphone market share erosion: Huawei's resurgence in China (Mate 60 series) and Apple's premium push could squeeze Xiaomi's mid-range.\n3. RSI overbought pullback: Short-term correction of 5-10% likely before next leg up. Position sizing must account for this.\n\n\n\nTIME HORIZON\n\n3-6 months — Hold through Q1 2025 earnings (expected Feb/March) when EV delivery numbers and smartphone recovery data will be clear. Exit if EV gross margin <12% or smartphone revenue continues declining.\n\n\n\nPAIR TRADE DIRECTION\n\nSince we are LONG Xiaomi, we SHORT a tech peer:\n\nTop 3 Pair Candidates (HK/A-share):\n\n1. SHORT Lenovo (0992.HK) — P/E 19.7x vs Xiaomi 14.9x, but Lenovo's PC market is structurally declining (no EV optionality). Same hardware margin pressure but no growth catalyst.\n\n2. SHORT Xiaomi's own warrants/derivatives — If available, shorting call options to fund the long position.\n\n3. SHORT Meituan (3690.HK) — P/E 28x, highly dependent on China consumption recovery. If stimulus disappoints, Meituan falls more than Xiaomi (which has hardware + EV diversification).\n\n\n\n最终决定：做多小米 (1810.HK)\n\n信心：高\n\n五大理由\n\n1. 基本面：14.9倍市盈率，较科技板块均值折价40%，市场完全未定价小米汽车（SU7预订单超10万）的期权价值。\n\n2. 技术面：短期突破MA5/MA20，成交量确认（1.19倍），54.79%的年度跌幅已耗尽卖压。RSI超买是反转初期特征。\n\n3. 情绪面：无数据=未被充分覆盖，任何正面催化剂（汽车交付、手机复苏）将产生超预期影响。\n\n4. 竞争面：12亿IoT设备生态+SU7性价比策略（21.6万 vs Model 3的24.6万），硬件分销网络协同效应被低估。\n\n5. 宏观面：中国消费刺激+EV补贴+全球手机周期见底（IDC预测2025年增长4%），地缘风险已定价。\n\n风险\n\n1. 汽车量产执行风险（毛利率低于10%）\n2. 华为/苹果挤压手机份额\n3. RSI超买后的短期回调（5-10%）\n\n时间跨度\n\n3-6个月，持有至2025年Q1财报（2-3月），观察汽车交付数据。\n\n配对交易\n\n做多小米，做空：\n1. 联想 (0992.HK) — 19.7倍PE，PC市场结构性下滑\n2. 美团 (3690.HK) — 28倍PE，消费复苏不及预期时跌幅更大",
  "pair_direction": "short",
  "top_candidates": [
    {
      "name": "理想汽车-HK",
      "ticker": "2015.HK",
      "score": 60.0
    },
    {
      "name": "浪潮信息",
      "ticker": "000977.SZ",
      "score": 60.0
    },
    {
      "name": "汇顶科技",
      "ticker": "603160.SS",
      "score": 58.0
    },
    {
      "name": "闻泰科技",
      "ticker": "600745.SS",
      "score": 58.0
    },
    {
      "name": "蔚来-HK",
      "ticker": "9866.HK",
      "score": 55.0
    },
    {
      "name": "科大讯飞",
      "ticker": "002230.SZ",
      "score": 55.0
    },
    {
      "name": "紫光股份",
      "ticker": "000938.SZ",
      "score": 55.0
    },
    {
      "name": "哔哩哔哩-HK",
      "ticker": "9626.HK",
      "score": 50.0
    },
    {
      "name": "商汤",
      "ticker": "0020.HK",
      "score": 45.0
    },
    {
      "name": "卓胜微",
      "ticker": "300782.SZ",
      "score": 43.0
    }
  ],
  "pair_recommendation": "UBS Portfolio Strategy: Pair Trade Recommendation\n\nTOP PICK: 浪潮信息 (000977.SZ)\nScore: 60/100 | Price: RMB 77.40 | Market Cap: RMB 113.66B\n\nWhy: 浪潮信息 trades at a PE of 44.7x—3x Xiaomi's 14.9x—despite negative revenue growth of -24.3% and razor-thin gross margins of 5.5%. The stock has rallied 20% in one month with no fundamental improvement, creating a textbook mean-reversion setup. Shorting this overvalued server maker against long Xiaomi captures both valuation compression and growth divergence.\n\nChinese Note (中文): 浪潮信息市盈率44.7倍，是小米14.9倍的三倍，但营收下降24.3%，毛利率仅5.5%。近期20%涨幅缺乏基本面支撑，适合做空配对。\n\n\n\nRUNNER-UP: 汇顶科技 (603160.SS)\nScore: 58/100 | Price: RMB 51.90 | Market Cap: RMB 24.18B\n\nWhy: PE of 31.6x vs Xiaomi's 14.9x with -9% revenue decline and -37% 6-month momentum. The fingerprint sensor leader faces structural headwinds from smartphone saturation and competition. However, lower liquidity and smaller market cap make it less ideal than 浪潮信息.\n\n\n\nPair Trade Thesis: LONG Xiaomi (1810.HK) + SHORT 浪潮信息 (000977.SZ)\n\nWhy This Combination Creates Alpha\n\n| Metric | Xiaomi (Long) | 浪潮信息 (Short) | Divergence |\n|--------|---------------|------------------|------------|\n| PE Ratio | 14.9x | 44.7x | 3.0x premium |\n| Revenue Growth | -10.9% | -24.3% | Xiaomi less negative |\n| Gross Margin | 22.1% | 5.5% | 4.0x advantage |\n| Operating Margin | 4.5% | 2.2% | 2.0x advantage |\n| 1M Momentum | +2.5% | +20.0% | Extreme divergence |\n| 3M Momentum | -15% | +13.3% | Opposite direction |\n\nAlpha Generation Mechanism: The trade exploits three simultaneous dislocations:\n1. Valuation mean-reversion – 浪潮信息's 44.7x PE is unsustainable given -24.3% revenue decline. Xiaomi's 14.9x PE is justified by its diversified IoT+EV ecosystem and 22% gross margins.\n2. Momentum reversal – 浪潮信息's 20% one-month rally is unsupported by fundamentals, while Xiaomi's recent weakness creates entry opportunity.\n3. Sector rotation – As AI capex enthusiasm fades, server hardware names like 浪潮信息 face earnings downgrades, while Xiaomi benefits from smartphone recovery and EV ramp.\n\nValuation Divergence Argument\n\n浪潮信息 is priced for perfection in a deteriorating business:\n- PE of 44.7x implies 20%+ earnings growth, yet revenue is declining 24.3%\n- PB of 5.1x is 2.3x Xiaomi's 2.25x, despite Xiaomi having positive ROE (14%) vs negative for 浪潮信息\n- EV/EBITDA of ~25x (estimated) vs Xiaomi's 18.7x – the server maker trades at a premium despite inferior economics\n\nXiaomi offers value with optionality:\n- 14.9x PE with 22% gross margins and 8% net margins\n- EV/EBITDA of 18.7x is reasonable for a company with smartphone recovery, IoT growth, and EV launch\n- Free cash flow of RMB 7.8B provides downside protection\n\nChinese Note (中文): 浪潮信息44.7倍市盈率对应营收下降24.3%，估值泡沫明显。小米14.9倍市盈率有22%毛利率和EV业务期权支撑，估值更合理。\n\nGrowth Trajectory Comparison\n\n| Growth Driver | Xiaomi (Long) | 浪潮信息 (Short) |\n|---------------|---------------|------------------|\n| Revenue Trend | -10.9% (cyclical bottom) | -24.3% (structural decline) |\n| Margin Trend | Expanding (EV, IoT) | Compressing (commodity servers) |\n| Key Catalyst | SU7 EV launch, smartphone recovery | AI server demand peaking |\n| Competitive Position | Strong brand, ecosystem moat | Low differentiation, price wars |\n\nXiaomi's growth inflection: Revenue decline of -10.9% is cyclical, driven by smartphone inventory correction. With SU7 EV launch in 2024 and global smartphone recovery, growth should turn positive in H2 2024. Gross margins are expanding from IoT and internet services.\n\n浪潮信息's structural decline: Revenue drop of -24.3% reflects commoditization of server hardware. AI server demand is real but competition from Huawei, Inspur, and Dell is intensifying. Gross margins of 5.5% leave no room for error. The company is a \"pick-and-shovel\" play in AI that has already been priced in.\n\nSector/Competitive Dynamics\n\nTechnology sector rotation is favoring Xiaomi:\n- Hardware cycle: Smartphones bottoming → Xiaomi benefits; AI servers peaking → 浪潮信息 vulnerable\n- Margin cycle: Xiaomi's margins expanding (EV, services); 浪潮信息's margins compressing (commodity hardware)\n- Valuation cycle: Xiaomi at 5-year low PE; 浪潮信息 at 3-year high PE\n\nChinese Note (中文): 行业轮动利好小米：智能手机周期见底，AI服务器需求见顶。小米利润率扩张，浪潮利润率压缩。\n\n\n\nCatalyst Timeline (3-6 Months)\n\n| Timeframe | Catalyst | Impact on Trade |\n|-----------|----------|-----------------|\n| 1-2 Months | Xiaomi Q1 2024 earnings (May) | Positive: SU7 orders, smartphone recovery |\n| 2-3 Months | 浪潮信息 Q1 earnings (April) | Negative: Revenue decline continues, margin pressure |\n| 3-4 Months | AI server demand data points | Negative for 浪潮信息: orders may slow |\n| 4-5 Months | Xiaomi SU7 delivery ramp | Positive: EV revenue recognition, margin expansion |\n| 5-6 Months | Global smartphone shipment data | Positive: Recovery trend confirms Xiaomi thesis |\n\nKey Near-Term Catalyst: 浪潮信息's Q1 2024 earnings (late April) will likely show continued revenue decline of -20%+ and margin compression. The stock's 20% rally means any disappointment will trigger sharp correction. Xiaomi's Q1 earnings (May) should show SU7 order momentum and smartphone recovery.\n\n\n\nRisk Analysis\n\n| Risk | Probability | Impact | Mitigation |\n|------|-------------|--------|------------|\n| AI server demand accelerates | Low-Medium | High (浪潮信息 rallies) | Use options, set stop-loss at 15% |\n| Xiaomi EV disappoints | Medium | Medium (Xiaomi falls) | Position size 60% of normal |\n| Market rally lifts all tech | Medium | Low (both rise, short hurts) | Beta-hedge with index futures |\n| Regulatory intervention | Low | High | Monitor policy, use HK shares |\n| Liquidity squeeze | Low | Medium | Limit position to 5% of portfolio |\n\nMaximum Risk: 15% loss if 浪潮信息 rallies 30% and Xiaomi falls 10% simultaneously. Mitigate with stop-loss at 15% of notional value.\n\nChinese Note (中文): 主要风险是AI服务器需求超预期或小米EV不及预期。建议设置15%止损，仓位控制在组合5%以内。\n\n\n\nConviction Level: HIGH (8/10)\n\nReasoning:\n1. Valuation gap is extreme – 3x PE premium for a company with worse growth and margins is unsustainable\n2. Momentum divergence is at 3-year extreme – 浪潮信息's 20% monthly gain vs -15% for Xiaomi creates mean-reversion opportunity\n3. Fundamental catalysts are aligned – Earnings seasons in April-May will validate the thesis\n4. Risk/reward is asymmetric – 浪潮信息 has 30% downside to fair value (30x PE on declining earnings) vs 15% upside risk\n5. Liquidity is adequate – Both stocks trade >$100M daily, allowing efficient execution\n\nThe only reason conviction is not 10/10: AI enthusiasm could persist longer than fundamentals justify. However, the 3-month catalyst timeline should be sufficient for mean-reversion.\n\nFinal Recommendation: Execute pair trade at 60% of normal position size, with stop-loss at 15% loss. Add to position if 浪潮信息 rallies another 10% without fundamental improvement.\n\nChinese Note (中文): 信心等级高（8/10）。估值差极端，动量背离创三年新高，基本面催化剂明确。建议60%正常仓位入场，设15%止损。"
}